{
  "workouts": [
    {
      "id": "0",
      "imageUrl":
        "https://images.unsplash.com/photo-1501116518234-f32f28802bd1?ixlib=rb-0.3.5&ixid=eyJhcHBfaWQiOjEyMDd9&s=f8a30c5d48a60731cf69f64d9d26939a&auto=format&fit=crop&w=1248&q=80",
      "title": "Muay Thai",
      "price": "60$",
      "userPhone": "041-425-900",
      "userEmail": "adam@gmail.com"
    },
    {
      "id": "1",
      "imageUrl":
        "https://images.unsplash.com/photo-1519008763396-77987f68def0?ixlib=rb-0.3.5&ixid=eyJhcHBfaWQiOjEyMDd9&s=1c9ada3f64a322ed14c3a3bd382f852a&auto=format&fit=crop&w=1490&q=80",
      "title": "CrossFit ",
      "price": "200$",
      "userPhone": "041-005-320",
      "userEmail": "stefan@gmail.com"
    },
    {
      "id": "2",
      "imageUrl":
        "https://images.unsplash.com/photo-1509009082772-cb9797f8adbf?ixlib=rb-0.3.5&ixid=eyJhcHBfaWQiOjEyMDd9&s=d227b77e8a3d66c9b7b58b73439aa4e5&auto=format&fit=crop&w=840&q=80",
      "title": "Yoga",
      "price": "127$",
      "userPhone": "041-125-400",
      "userEmail": "davids@gmail.com"
    },
    {
      "id": "3",
      "imageUrl":
        "https://images.unsplash.com/photo-1521804906057-1df8fdb718b7?ixlib=rb-0.3.5&ixid=eyJhcHBfaWQiOjEyMDd9&s=f831342881cb6ff58e50698c7f9432de&auto=format&fit=crop&w=1350&q=80  ",
      "title": "WeightLifting",
      "price": "99$",
      "userPhone": "041-505-300",
      "userEmail": "johnwi@gmail.com"
    },
    {
      "id": "4",
      "imageUrl":
        "https://images.unsplash.com/photo-1516208962313-9d183d94f577?ixlib=rb-0.3.5&ixid=eyJhcHBfaWQiOjEyMDd9&s=d158f9d9dfbb3692c9b6d5e105631bda&auto=format&fit=crop&w=1334&q=80",
      "title": "Calisthenics Workout",
      "price": "65$",
      "userPhone": "041-525-800",
      "userEmail": "richards@gmail.com"
    },
    {
      "id": "5",
      "imageUrl":
        "https://images.unsplash.com/photo-1466761366829-84fd59a22e0b?ixlib=rb-0.3.5&ixid=eyJhcHBfaWQiOjEyMDd9&s=d8695676291efbbe6a723dcd1fe3bd88&auto=format&fit=crop&w=1351&q=80",
      "title": "Running",
      "price": "147$",
      "userPhone": "041-142-200",
      "userEmail": "richy@gmail.com"
    },
    {
      "id": "6",
      "imageUrl":
        "https://images.unsplash.com/photo-1522898467493-49726bf28798?ixlib=rb-0.3.5&ixid=eyJhcHBfaWQiOjEyMDd9&s=416bda526de26f2ac93016273f55a633&auto=format&fit=crop&w=1500&q=80",
      "title": "Pilates Workout",
      "price": "139$",
      "userPhone": "041-424-300",
      "userEmail": "alissa@gmail.com"
    },
    {
      "id": "7",
      "imageUrl":
        "https://images.unsplash.com/photo-1515025617920-e1e674b5033c?ixlib=rb-0.3.5&ixid=eyJhcHBfaWQiOjEyMDd9&s=aa18df38d40873a258a71fa0838c6f08&auto=format&fit=crop&w=1628&q=80",
      "title": "Brazilian Jiu-Jitsu",
      "price": "130$",
      "userPhone": "041-625-500",
      "userEmail": "adamsmith@gmail.com"
    },
    {
      "id": "8",
      "imageUrl":
        "https://images.unsplash.com/photo-1495555687398-3f50d6e79e1e?ixlib=rb-0.3.5&ixid=eyJhcHBfaWQiOjEyMDd9&s=f5bd26422b6425d05274c92a51e1e16d&auto=format&fit=crop&w=1350&q=80",
      "title": "Boxing",
      "price": "200$",
      "userPhone": "041-001-320",
      "userEmail": "jess@gmail.com"
    }
  ]
}